requests/__init__.py
requests/__version__.py
requests/_internal_utils.py
requests/adapters.py
requests/api.py
requests/auth.py
requests/certs.py
requests/compat.py
requests/cookies.py
requests/exceptions.py
requests/hooks.py
requests/models.py
requests/sessions.py
requests/status_codes.py
requests/structures.py
requests/utils.py
requests2-2.16.0.dist-info/DESCRIPTION.rst
requests2-2.16.0.dist-info/METADATA
requests2-2.16.0.dist-info/RECORD
requests2-2.16.0.dist-info/WHEEL
requests2-2.16.0.dist-info/metadata.json
requests2-2.16.0.dist-info/top_level.txt
